<?xml version="1.0" encoding="UTF-8" standalone="no"?><review id="197" item="Circus Circus Hotel &amp; Casino" rating="2">
	<title>
		<sentence id="1">
			Circus-Circus(1) do(2) not(3) You(4) Deserve(5) Better(6) in(7) Vegas(8) -(9) Treat(10) Yourself(11) to(12) Something(13) Better(14) 
		</sentence>
	</title>
	<pros>
		<sentence id="1">
			Cheap(1) ,(2) clean(3) ,(4) utilitarian(5) 
			<opinion feature="hotel" opWords="1" polarity="+"/>
			<opinion feature="hotel" opWords="3" polarity="+"/>
			<opinion feature="hotel" opWords="5" polarity="+"/>
		</sentence>
	</pros>
	<cons>
		<sentence id="1">
			Cheap(1) ,(2) poor(3) location(4) ,(5) basic(6) casino(7) 
			<opinion feature="hotel" opWords="1" polarity="+"/>
			<opinion featWords="4" feature="place" opWords="3" polarity="-"/>
		</sentence>
	</cons>
	<bottomLine>
		<sentence id="1">
			Vegas(1) on(2) the(3) cheap(4) and(5) it(6) 's(7) not(8) cheaper(9) than(10) this(11) .(12) 
		</sentence>
		<sentence id="2">
			I(1) 'd(2) spend(3) an(4) extra(5) $30(6) a(7) night(8) and(9) stay(10) at(11) a(12) much(13) finer(14) hotel(15) further(16) south(17) on(18) the(19) strip(20) .(21) 
		</sentence>
	</bottomLine>
	<text>
		<sentence id="1">
			I(1) had(2) been(3) to(4) Las(5) Vegas(6) once(7) before(8) and(9) I(10) was(11) too(12) young(13) to(14) gamble(15) and(16) we(17) never(18) actually(19) stayed(20) in(21) Vegas(22) ,(23) just(24) passed(25) through(26) the(27) airport(28) .(29) 
		</sentence>
		<sentence id="2">
			So(1) when(2) I(3) was(4) making(5) reservations(6) for(7) my(8) first(9) lt(10) trip(11) to(12) Vegas(13) ,(14) I(15) was(16) 'nt(17) really(18) sure(19) what(20) I(21) was(22) looking(23) for(24) and(25) really(26) had(27) no(28) idea(29) where(30) I(31) should(32) stay(33) .(34) 
		</sentence>
		<sentence id="3">
			As(1) visiting(2) Vegas(3) was(4) part(5) of(6) a(7) much(8) larger(9) vacation(10) that(11) was(12) costing(13) my(14) partner(15) and(16) I(17) oodles(18) and(19) oodles(20) of(21) money(22) ,(23) I(24) focused(25) on(26) booking(27) a(28) room(29) at(30) a(31) reasonably(32) affordable(33) hotel(34) on(35) the(36) Las(37) Vegas(38) Strip(39) .(40) 
			<opinion featWords="34" feature="hotel" opWords="33" polarity="+"/>
		</sentence>
		<sentence id="4">
			I(1) searched(2) ,(3) I(4) searched(5) and(6) searched(7) and(8) finally(9) settled(10) on(11) Circus(12) Circus(13) .(14) 
		</sentence>
		<sentence id="5">
			It(1) was(2) the(3) cheapest(4) out(5) of(6) all(7) the(8) strip(9) hotels(10) and(11) really(12) ,(13) all(14) that(15) I(16) was(17) looking(18) for(19) was(20) a(21) room(22) and(23) a(24) place(25) to(26) be(27) able(28) to(29) take(30) a(31) shower(32) ,(33) not(34) too(35) much(36) more(37) .(38) 
			<opinion feature="price" opWords="4" polarity="+"/>
		</sentence>
		<sentence id="6">
			Mind(1) you(2) ,(3) I(4) have(5) never(6) really(7) been(8) a(9) fan(10) of(11) circuses(12) to(13) start(14) with(15) .(16) 
		</sentence>
		<sentence id="7">
			We(1) arrived(2) late(3) in(4) the(5) afternoon(6) at(7) Circus(8) Circus(9) ,(10) after(11) coming(12) over(13) from(14) just(15) finishing(16) a(17) hike(18) down(19) and(20) back(21) up(22) the(23) Grand(24) Canyon(25) .(26) 
		</sentence>
		<sentence id="8">
			We(1) were(2) tired(3) ,(4) we(5) were(6) cranky(7) and(8) we(9) just(10) were(11) 'nt(12) in(13) the(14) mood(15) to(16) deal(17) with(18) stuff(19) .(20) 
		</sentence>
		<sentence id="9">
			That(1) s(2) probably(3) why(4) the(5) parking(6) garage(7) annoyed(8) me(9) as(10) we(11) finally(12) got(13) there(14) .(15) 
		</sentence>
		<sentence id="10">
			As(1) you(2) are(3) on(4) the(5) strip(6) and(7) going(8) by(9) Circus(10) Circus(11) ,(12) there(13) s(14) an(15) itty(16) bitty(17) little(18) sign(19) that(20) says(21) parking(22) and(23) once(24) you(25) get(26) into(27) the(28) parking(29) areas(30) and(31) garages(32) ,(33) there(34) is(35) nothing(36) telling(37) you(38) where(39) in(40) relationship(41) to(42) the(43) hotel(44) check-in(45) you(46) are(47) .(48) 
		</sentence>
		<sentence id="11">
			I(1) found(2) a(3) spot(4) ((5) which(6) was(7) a(8) challenge(9) in(10) of(11) itself(12) )(13) and(14) we(15) went(16) in(17) to(18) try(19) to(20) find(21) the(22) check-in(23) .(24) 
		</sentence>
		<sentence id="12">
			Thank(1) God(2) we(3) did(4) 'nt(5) carry(6) our(7) bags(8) with(9) us(10) ,(11) otherwise(12) we(13) would(14) have(15) been(16) backpacking(17) even(18) more(19) than(20) we(21) did(22) at(23) the(24) Grand(25) Canyon(26) .(27) 
		</sentence>
		<sentence id="13">
			So(1) if(2) you(3) are(4) driving(5) into(6) Circus(7) Circus(8) ,(9) make(10) sure(11) that(12) you(13) try(14) to(15) park(16) as(17) close(18) to(19) the(20) doors(21) as(22) possible(23) ,(24) even(25) though(26) the(27) check-in(28) is(29) still(30) a(31) haul(32) from(33) those(34) doors(35) .(36) 
		</sentence>
		<sentence id="14">
			That(1) or(2) just(3) pay(4) someone(5) to(6) carry(7) your(8) bags(9) for(10) you(11) .(12) 
		</sentence>
		<sentence id="15">
			The(1) first(2) thing(3) I(4) noticed(5) when(6) we(7) walked(8) in(9) ((10) or(11) actually(12) got(13) to(14) the(15) door(16) )(17) is(18) that(19) everything(20) in(21) this(22) hotel(23) has(24) a(25) circus(26) theme(27) ((28) hence(29) Circus(30) Circus(31) ,(32) I(33) know(34) )(35) .(36) 
		</sentence>
		<sentence id="16">
			However(1) ,(2) the(3) outside(4) of(5) the(6) casino(7) /(8) hotel(9) and(10) the(11) inside(12) of(13) the(14) building(15) are(16) two(17) complete(18) opposites(19) .(20) 
		</sentence>
		<sentence id="17">
			Outside(1) they(2) are(3) projecting(4) that(5) typical(6) American(7) type(8) circus(9) theme(10) you(11) know(12) ,(13) the(14) big(15) top(16) flashy(17) lights(18) ,(19) clowns(20) ,(21) etc.(22) However(23) on(24) the(25) inside(26) ,(27) it(28) appears(29) that(30) they(31) are(32) going(33) for(34) the(35) older(36) Parisian(37) circus(38) feel(39) .(40) 
		</sentence>
		<sentence id="18">
			There(1) are(2) all(3) these(4) paintings(5) of(6) circus(7) scenes(8) and(9) everything(10) is(11) designed(12) with(13) that(14) old(15) time(16) feeling(17) in(18) mind(19) .(20) 
		</sentence>
		<sentence id="19">
			It(1) is(2) a(3) very(4) strange(5) dichotomy(6) between(7) the(8) inside(9) and(10) the(11) outside(12) .(13) 
		</sentence>
		<sentence id="20">
			So(1) we(2) find(3) the(4) check(5) in(6) and(7) it(8) was(9) fairly(10) straightforward(11) .(12) 
		</sentence>
		<sentence id="21">
			I(1) had(2) already(3) paid(4) for(5) the(6) room(7) ,(8) so(9) really(10) all(11) I(12) had(13) to(14) do(15) was(16) show(17) ID(18) and(19) put(20) a(21) credit(22) card(23) down(24) in(25) case(26) we(27) used(28) room(29) service(30) or(31) the(32) telephone(33) or(34) what-have-you(35) .(36) 
		</sentence>
		<sentence id="22">
			The(1) lines(2) were(3) long(4) and(5) we(6) probably(7) waited(8) to(9) check(10) in(11) for(12) about(13) an(14) hour(15) .(16) 
		</sentence>
		<sentence id="23">
			I(1) amm(2) not(3) sure(4) if(5) it(6) was(7) a(8) busy(9) time(10) of(11) the(12) day(13) ((14) 3pm(15) )(16) and(17) it(18) appeared(19) that(20) there(21) really(22) were(23) 'nt(24) that(25) many(26) people(27) working(28) so(29) maybe(30) it(31) was(32) just(33) a(34) bad(35) day(36) for(37) them(38) .(39) 
		</sentence>
		<sentence id="24">
			However(1) ,(2) over(3) the(4) next(5) few(6) days(7) walking(8) by(9) the(10) check-in(11) lobby(12) ,(13) there(14) was(15) always(16) quite(17) a(18) line(19) .(20) 
		</sentence>
		<sentence id="25">
			We(1) went(2) back(3) out(4) to(5) the(6) car(7) and(8) got(9) our(10) bags(11) and(12) then(13) headed(14) up(15) to(16) find(17) our(18) rooms(19) .(20) 
		</sentence>
		<sentence id="26">
			The(1) entire(2) building(3) was(4) not(5) designed(6) with(7) ease(8) of(9) travel(10) in(11) mind(12) .(13) 
		</sentence>
		<sentence id="27">
			Several(1) areas(2) throughout(3) the(4) first(5) floor(6) ((7) which(8) hold(9) the(10) casinos(11) and(12) the(13) hotel(14) lobby(15) )(16) appear(17) to(18) look(19) the(20) same(21) and(22) most(23) everything(24) eventually(25) loops(26) right(27) back(28) around(29) so(30) you(31) can(32) end(33) up(34) walking(35) in(36) circles(37) for(38) quite(39) some(40) time(41) until(42) you(43) realize(44) that(45) you(46) are(47) back(48) to(49) where(50) you(51) started(52) .(53) 
		</sentence>
		<sentence id="28">
			In(1) addition(2) the(3) areas(4) where(5) the(6) elevators(7) are(8) all(9) look(10) the(11) same(12) ,(13) so(14) unless(15) you(16) are(17) paying(18) attention(19) ,(20) you(21) can(22) go(23) to(24) your(25) floor(26) ,(27) but(28) be(29) completely(30) on(31) the(32) other(33) side(34) of(35) the(36) tower(37) or(38) in(39) a(40) different(41) part(42) of(43) the(44) hotel(45) .(46) 
		</sentence>
		<sentence id="29">
			This(1) is(2) very(3) confusing(4) ,(5) especially(6) since(7) every(8) hotel(9) floor(10) looks(11) exactly(12) the(13) same(14) .(15) 
		</sentence>
		<sentence id="30">
			The(1) room(2) was(3) good(4) enough(5) .(6) 
			<opinion featWords="2" feature="rooms" opWords="4,5" polarity="+"/>
		</sentence>
		<sentence id="31">
			I(1) heaved(2) a(3) sigh(4) of(5) relief(6) when(7) I(8) realized(9) that(10) there(11) were(12) no(13) circus(14) themed(15) items(16) in(17) the(18) room(19) .(20) 
		</sentence>
		<sentence id="32">
			At(1) the(2) very(3) least(4) ,(5) you(6) have(7) the(8) room(9) to(10) escape(11) from(12) it(13) all(14) if(15) you(16) can(17) not(18) stand(19) the(20) circus(21) ((22) at(23) least(24) until(25) you(26) turn(27) their(28) TV(29) channel(30) on(31) and(32) see(33) their(34) ief(35) Clown(36) Officer(37) )(38) .(39) 
		</sentence>
		<sentence id="33">
			We(1) had(2) gotten(3) a(4) room(5) with(6) a(7) single(8) king(9) size(10) bed(11) .(12) 
		</sentence>
		<sentence id="34">
			In(1) addition(2) to(3) the(4) bed(5) ,(6) there(7) was(8) a(9) desk(10) ,(11) table(12) ,(13) two(14) chairs(15) and(16) then(17) we(18) had(19) the(20) bathroom(21) .(22) 
		</sentence>
		<sentence id="35">
			Men(1) make(2) sure(3) you(4) put(5) the(6) toilet(7) seat(8) all(9) the(10) way(11) up(12) or(13) it(14) will(15) fall(16) down(17) while(18) you(19) are(20) in(21) the(22) middle(23) of(24) using(25) the(26) toilet(27) it(28) can(29) get(30) kind(31) of(32) annoying(33) .(34) 
		</sentence>
		<sentence id="36">
			The(1) TV(2) had(3) all(4) the(5) basic(6) cable(7) channels(8) ,(9) no(10) pay(11) networks(12) like(13) HBO(14) or(15) anything(16) though(17) .(18) 
		</sentence>
		<sentence id="37">
			After(1) resting(2) up(3) a(4) bit(5) the(6) casinos(7) in(8) Circus(9) Circus(10) were(11) the(12) first(13) we(14) hit(15) .(16) 
		</sentence>
		<sentence id="38">
			Once(1) again(2) ,(3) I(4) like(5) to(6) say(7) that(8) this(9) casino(10) appears(11) to(12) have(13) been(14) designed(15) to(16) confuse(17) people(18) and(19) make(20) them(21) get(22) lost(23) ,(24) more(25) so(26) than(27) the(28) average(29) casino(30) .(31) 
		</sentence>
		<sentence id="39">
			Moe(1) and(2) I(3) spent(4) quite(5) a(6) bit(7) of(8) time(9) ,(10) even(11) after(12) being(13) there(14) for(15) 2(16) nights(17) ,(18) wandering(19) around(20) trying(21) to(22) get(23) our(24) bearings(25) .(26) 
		</sentence>
		<sentence id="40">
			It(1) was(2) time(3) consuming(4) and(5) just(6) frustrating(7) .(8) 
		</sentence>
		<sentence id="41">
			The(1) two(2) casinos(3) at(4) Circus(5) Circus(6) are(7) not(8) large(9) by(10) strip(11) standards(12) ,(13) but(14) they(15) were(16) never(17) overly(18) crowded(19) while(20) we(21) were(22) there(23) and(24) provided(25) a(26) decent(27) selection(28) of(29) slot(30) machines(31) and(32) table(33) games(34) .(35) 
		</sentence>
		<sentence id="42">
			In(1) all(2) honesty(3) ,(4) out(5) of(6) the(7) rest(8) of(9) the(10) casinos(11) on(12) the(13) strip(14) ,(15) we(16) played(17) the(18) longest(19) at(20) Circus(21) Circus(22) and(23) spent(24) the(25) least(26) amount(27) of(28) money(29) .(30) 
		</sentence>
		<sentence id="43">
			One(1) slot(2) machine(3) I(4) played(5) for(6) 3(7) hours(8) on(9) $2(10) now(11) that(12) 's(13) entertainment(14) value(15) for(16) your(17) money(18) .(19) 
		</sentence>
		<sentence id="44">
			However(1) ,(2) if(3) you(4) are(5) looking(6) for(7) the(8) latest(9) and(10) greatest(11) slot(12) machines(13) ,(14) or(15) fancy(16) tables(17) and(18) finely(19) decorated(20) casino(21) floors(22) this(23) is(24) not(25) the(26) place(27) for(28) you(29) .(30) 
		</sentence>
		<sentence id="45">
			While(1) there(2) is(3) an(4) acrobatic(5) circus(6) occurring(7) during(8) daytime(9) hours(10) over(11) the(12) main(13) casino(14) the(15) two(16) of(17) us(18) very(19) every(20) rarely(21) looked(22) up(23) to(24) watch(25) it(26) we(27) were(28) either(29) play(30) or(31) we(32) were(33) wandering(34) around(35) trying(36) to(37) find(38) the(39) exit(40) .(41) 
		</sentence>
		<sentence id="46">
			The(1) location(2) of(3) Circus(4) Circus(5) is(6) also(7) very(8) poor(9) for(10) anyone(11) interested(12) in(13) visiting(14) the(15) rest(16) of(17) the(18) strip(19) .(20) 
			<opinion featWords="2" feature="place" opWords="9" polarity="-" potency="8"/>
		</sentence>
		<sentence id="47">
			It(1) s(2) about(3) 2(4) miles(5) north(6) of(7) the(8) south(9) end(10) of(11) the(12) strip(13) .(14) 
		</sentence>
		<sentence id="48">
			So(1) that(2) means(3) ,(4) unless(5) you(6) take(7) a(8) taxi(9) it(10) s(11) quite(12) a(13) haul(14) to(15) just(16) about(17) any(18) of(19) the(20) major(21) casinos(22) towards(23) the(24) southern(25) end(26) of(27) the(28) strip(29) like(30) Treasure(31) Island(32) ,(33) New(34) York-New(35) York(36) ,(37) Paris(38) ,(39) and(40) MGM(41) to(42) just(43) name(44) a(45) few(46) .(47) 
		</sentence>
		<sentence id="49">
			Moe(1) and(2) I(3) spent(4) probably(5) about(6) the(7) time(8) we(9) at(10) Vegas(11) walking(12) back(13) and(14) forth(15) and(16) every(17) night(18) we(19) had(20) that(21) long(22) walk(23) to(24) look(25) forward(26) to(27) .(28) 
		</sentence>
		<sentence id="50">
			Bottom(1) line(2) if(3) you(4) want(5) to(6) do(7) Vegas(8) cheap(9) you(10) are(11) 'nt(12) going(13) to(14) get(15) any(16) cheaper(17) than(18) Circus(19) City(20) but(21) you(22) will(23) end(24) up(25) with(26) a(27) fairly(28) basic(29) hotel(30) and(31) casino(32) and(33) you(34) will(35) end(36) up(37) walking(38) miles(39) or(40) spending(41) lots(42) of(43) money(44) on(45) taxis(46) if(47) you(48) want(49) to(50) visit(51) the(52) rest(53) of(54) the(55) Strip(56) .(57) 
			<opinion featWords="30" feature="hotel" opWords="29" polarity="+" potency="28"/>
		</sentence>
		<sentence id="51">
			Probably(1) the(2) only(3) people(4) that(5) will(6) really(7) enjoy(8) Circus(9) Circus(10) would(11) be(12) children(13) who(14) are(15) forced(16) to(17) go(18) to(19) Vegas(20) with(21) their(22) parents(23) .(24) 
		</sentence>
		<sentence id="52">
			They(1) can(2) watch(3) the(4) circus(5) ,(6) or(7) spend(8) their(9) parents(10) money(11) in(12) the(13) indoor(14) theme(15) park(16) that(17) the(18) hotel(19) /(20) casino(21) has(22) ((23) it(24) is(25) not(26) great(27) ,(28) but(29) is(30) okay(31) -(32) I(33) did(34) not(35) go(36) on(37) any(38) rides(39) )(40) .(41) 
		</sentence>
		<sentence id="53">
			I(1) 'd(2) spend(3) an(4) extra(5) $20(6) to(7) $30(8) a(9) night(10) and(11) stay(12) at(13) a(14) hotel(15) much(16) further(17) south(18) on(19) the(20) strip(21) with(22) much(23) nicer(24) accomodations(25) .(26) 
		</sentence>
		<sentence id="54">
			You(1) really(2) do(3) not(4) save(5) all(6) that(7) much(8) with(9) Circus(10) Circus(11) when(12) you(13) consider(14) the(15) cons(16) .(17) 
		</sentence>
		<sentence id="55">
			My(1) guide(2) to(3) the(4) Las(5) Vegas(6) Strip(7) -(8) hotels(9) ,(10) attractions(11) ,(12) food(13) and(14) more(15) !(16) 
		</sentence>
		<sentence id="56">
			More(1) Vegas(2) Attractions(3) &amp;(4) Information(5) THEHotel(6) at(7) Mandalay(8) Bay(9) /(10) The(11) Mirage(12) Hotel(13) &amp;(14) Casino(15) /(16) The(17) Monte(18) Carlo(19) Hotel(20) &amp;(21) Casino(22) -(23) TI(24) -(25) Treasure(26) Island(27) Hotel(28) &amp;(29) Casino(30) /(31) Buccaneer(32) Bay(33) Pirate(34) Battle(35) at(36) Treasure(37) Island(38) /(39) New(40) York-New(41) York(42) Hotel(43) /(44) Casino(45) /(46) Red(47) Rock(48) Canyon(49) Recreation(50) Area(51) /(52) Mandalay(53) Bay(54) Hotel(55) /(56) Casino(57) /(58) Excalibur(59) Hotel(60) /(61) Casino(62) /(63) Circus(64) Circus(65) Hotel(66) /(67) Casino(68) /(69) Q(70) Vegas(71) Magazine(72) ((73) LGBT(74) )(75) /(76) The(77) Shark(78) Reef(79) at(80) Mandalay(81) Bay(82) 
		</sentence>
	</text>
</review>