<?xml version="1.0" encoding="UTF-8" standalone="no"?><review id="607" item="New Yorker Ramada" rating="3">
	<title>
		<sentence id="1">
			It(1) 's(2) not(3) so(4) bad(5) 
			<opinion feature="hotel" opWords="3,5" polarity="+" potency="4"/>
		</sentence>
	</title>
	<pros>
		<sentence id="1">
			Clean(1) Good(2) sized(3) room(4) 
		</sentence>
	</pros>
	<cons>
		<sentence id="1">
			Wind(1) going(2) through(3) air(4) conditioner(5) unit(6) is(7) very(8) loud(9) 
			<opinion featWords="4,5,6" feature="air conditioning units" opWords="9" polarity="-" potency="8"/>
		</sentence>
	</cons>
	<text>
		<sentence id="1">
			I(1) was(2) nervous(3) to(4) stay(5) here(6) after(7) reading(8) the(9) previous(10) reviews(11) ,(12) but(13) it(14) turned(15) out(16) to(17) not(18) be(19) bad(20) at(21) all(22) .(23) 
		</sentence>
		<sentence id="2">
			We(1) were(2) in(3) a(4) room(5) with(6) a(7) king(8) bed(9) on(10) the(11) 36th(12) floor(13) ,(14) and(15) though(16) it(17) was(18) not(19) "(20) the(21) Ritz(22) "(23) it(24) was(25) clean(26) ((27) my(28) main(29) priority(30) in(31) a(32) hotel(33) )(34) and(35) nicely(36) sized(37) for(38) a(39) hotel(40) room(41) in(42) NYC(43) .(44) 
			<opinion featWords="41" feature="rooms" opWords="26" polarity="+"/>
			<opinion featWords="41" feature="rooms" opWords="36,37" polarity="+"/>
		</sentence>
		<sentence id="3">
			We(1) had(2) our(3) 5-month(4) old(5) baby(6) with(7) us(8) ,(9) and(10) I(11) was(12) comfortable(13) having(14) her(15) stay(16) in(17) this(18) hotel(19) .(20) 
		</sentence>
		<sentence id="4">
			The(1) first(2) night(3) it(4) was(5) very(6) windy(7) and(8) the(9) wind(10) going(11) through(12) the(13) window(14) air(15) conditioning(16) unit(17) was(18) very(19) loud(20) ,(21) so(22) I(23) would(24) recommend(25) bringing(26) ear(27) plugs(28) .(29) 
			<opinion featWords="15,16,17" feature="air conditioning units" opWords="20" polarity="-" potency="19"/>
		</sentence>
		<sentence id="5">
			As(1) others(2) report(3) ,(4) it(5) is(6) in(7) a(8) good(9) location(10) .(11) 
			<opinion featWords="10" feature="place" opWords="9" polarity="+"/>
		</sentence>
		<sentence id="6">
			The(1) staff(2) was(3) friendly(4) .(5) 
			<opinion featWords="2" feature="staff" opWords="4" polarity="+"/>
		</sentence>
		<sentence id="7">
			We(1) did(2) have(3) to(4) wait(5) a(6) long(7) time(8) to(9) store(10) our(11) luggage(12) after(13) check-out(14) ,(15) but(16) we(17) chose(18) to(19) do(20) that(21) right(22) at(23) noon(24) ((25) check-out(26) time(27) )(28) so(29) the(30) line(31) might(32) not(33) always(34) be(35) so(36) bad(37) .(38) 
		</sentence>
		<sentence id="8">
			In(1) summary(2) ,(3) I(4) think(5) this(6) is(7) a(8) fine(9) hotel(10) to(11) stay(12) at(13) if(14) you(15) want(16) to(17) be(18) right(19) in(20) convenient(21) Manhattan(22) and(23) not(24) pay(25) too(26) much(27) money(28) .(29) 
			<opinion featWords="10" feature="hotel" opWords="9" polarity="+"/>
		</sentence>
	</text>
</review>